secmeasure/__init__.py
secmeasure-0.1.2.dist-info/METADATA
secmeasure-0.1.2.dist-info/WHEEL
secmeasure-0.1.2.dist-info/top_level.txt
secmeasure-0.1.2.dist-info/RECORD
