Metadata-Version: 2.4
Name: secmeasure
Version: 0.1.2
Summary: Library for cleaning strings and applying security measures to requests URLs.
Author-email: Conde <billordowiyi@gmail.com>
Requires-Python: >=3.6
